GinKuangjiaKaifaYuShizhan/README.md
GinKuangjiaKaifaYuShizhan/__init__.py
GinKuangjiaKaifaYuShizhan/__main__.py
GinKuangjiaKaifaYuShizhan/file.epub
GinKuangjiaKaifaYuShizhan/index.html
GinKuangjiaKaifaYuShizhan/css/__init__.py
GinKuangjiaKaifaYuShizhan/css/annotations.css
GinKuangjiaKaifaYuShizhan/css/main.css
GinKuangjiaKaifaYuShizhan/css/normalize.css
GinKuangjiaKaifaYuShizhan/css/popup.css
GinKuangjiaKaifaYuShizhan/font/__init__.py
GinKuangjiaKaifaYuShizhan/font/fontello.eot
GinKuangjiaKaifaYuShizhan/font/fontello.svg
GinKuangjiaKaifaYuShizhan/font/fontello.ttf
GinKuangjiaKaifaYuShizhan/font/fontello.woff
GinKuangjiaKaifaYuShizhan/img/__init__.py
GinKuangjiaKaifaYuShizhan/img/annotator-glyph-sprite.png
GinKuangjiaKaifaYuShizhan/img/annotator-icon-sprite.png
GinKuangjiaKaifaYuShizhan/img/apple-touch-icon.png
GinKuangjiaKaifaYuShizhan/img/cancelfullscreen.png
GinKuangjiaKaifaYuShizhan/img/close.png
GinKuangjiaKaifaYuShizhan/img/fullscreen.png
GinKuangjiaKaifaYuShizhan/img/loader.gif
GinKuangjiaKaifaYuShizhan/img/menu-icon.png
GinKuangjiaKaifaYuShizhan/img/save.png
GinKuangjiaKaifaYuShizhan/img/saved.png
GinKuangjiaKaifaYuShizhan/img/settings-s.png
GinKuangjiaKaifaYuShizhan/img/settings.png
GinKuangjiaKaifaYuShizhan/img/star.png
GinKuangjiaKaifaYuShizhan/js/__init__.py
GinKuangjiaKaifaYuShizhan/js/epub.js
GinKuangjiaKaifaYuShizhan/js/epub.min.js
GinKuangjiaKaifaYuShizhan/js/epub.min.map
GinKuangjiaKaifaYuShizhan/js/hooks.min.js
GinKuangjiaKaifaYuShizhan/js/hooks.min.map
GinKuangjiaKaifaYuShizhan/js/reader.js
GinKuangjiaKaifaYuShizhan/js/reader.js.map
GinKuangjiaKaifaYuShizhan/js/reader.min.js
GinKuangjiaKaifaYuShizhan/js/reader.min.map
GinKuangjiaKaifaYuShizhan/js/hooks/__init__.py
GinKuangjiaKaifaYuShizhan/js/hooks/extensions/__init__.py
GinKuangjiaKaifaYuShizhan/js/hooks/extensions/highlight.js
GinKuangjiaKaifaYuShizhan/js/libs/__init__.py
GinKuangjiaKaifaYuShizhan/js/libs/jquery.min.js
GinKuangjiaKaifaYuShizhan/js/libs/localforage.min.js
gin_kuangjia_kaifa_yu_shizhan-2024.3.5.0.dist-info/METADATA
gin_kuangjia_kaifa_yu_shizhan-2024.3.5.0.dist-info/WHEEL
gin_kuangjia_kaifa_yu_shizhan-2024.3.5.0.dist-info/entry_points.txt
gin_kuangjia_kaifa_yu_shizhan-2024.3.5.0.dist-info/top_level.txt
gin_kuangjia_kaifa_yu_shizhan-2024.3.5.0.dist-info/RECORD
